key_value/aio/__init__.py
key_value/aio/adapters/__init__.py
key_value/aio/adapters/pydantic/__init__.py
key_value/aio/adapters/pydantic/adapter.py
key_value/aio/adapters/raise_on_missing/__init__.py
key_value/aio/adapters/raise_on_missing/adapter.py
key_value/aio/protocols/__init__.py
key_value/aio/protocols/key_value.py
key_value/aio/py.typed
key_value/aio/stores/base.py
key_value/aio/stores/disk/__init__.py
key_value/aio/stores/disk/multi_store.py
key_value/aio/stores/disk/store.py
key_value/aio/stores/dynamodb/__init__.py
key_value/aio/stores/dynamodb/store.py
key_value/aio/stores/elasticsearch/__init__.py
key_value/aio/stores/elasticsearch/store.py
key_value/aio/stores/elasticsearch/utils.py
key_value/aio/stores/keyring/__init__.py
key_value/aio/stores/keyring/store.py
key_value/aio/stores/memcached/__init__.py
key_value/aio/stores/memcached/store.py
key_value/aio/stores/memory/__init__.py
key_value/aio/stores/memory/store.py
key_value/aio/stores/mongodb/__init__.py
key_value/aio/stores/mongodb/store.py
key_value/aio/stores/null/__init__.py
key_value/aio/stores/null/store.py
key_value/aio/stores/redis/__init__.py
key_value/aio/stores/redis/store.py
key_value/aio/stores/rocksdb/__init__.py
key_value/aio/stores/rocksdb/store.py
key_value/aio/stores/simple/__init__.py
key_value/aio/stores/simple/store.py
key_value/aio/stores/valkey/__init__.py
key_value/aio/stores/valkey/store.py
key_value/aio/stores/vault/__init__.py
key_value/aio/stores/vault/store.py
key_value/aio/wrappers/__init__.py
key_value/aio/wrappers/base.py
key_value/aio/wrappers/compression/__init__.py
key_value/aio/wrappers/compression/wrapper.py
key_value/aio/wrappers/encryption/__init__.py
key_value/aio/wrappers/encryption/wrapper.py
key_value/aio/wrappers/fallback/__init__.py
key_value/aio/wrappers/fallback/wrapper.py
key_value/aio/wrappers/limit_size/__init__.py
key_value/aio/wrappers/limit_size/wrapper.py
key_value/aio/wrappers/logging/__init__.py
key_value/aio/wrappers/logging/wrapper.py
py_key_value_aio-0.2.7.dist-info/WHEEL
py_key_value_aio-0.2.7.dist-info/METADATA
py_key_value_aio-0.2.7.dist-info/RECORD
